<?xml version='1.0' encoding='utf-8'?>
<!-- FreeCAD DocumentObject -->
<Document SchemaVersion="4" FileVersion="2">
<Object name="Solid090">
  <Properties Count="8" TransientCount="1">
    <_Property name="_ElementMapVersion" type="App::PropertyString" status="234881024"/>
    <Property name="ColoredElements" type="App::PropertyLinkSubHidden" status="218103808">
      <LinkSub value="" count="0">
      </LinkSub>
    </Property>
    <Property name="ExpressionEngine" type="App::PropertyExpressionEngine" status="67108864">
      <ExpressionEngine count="0"></ExpressionEngine>
    </Property>
    <Property name="Label" type="App::PropertyString" status="134217728">
      <String value="Unnamed"/>
    </Property>
    <Property name="Label2" type="App::PropertyString" status="128">
      <String value=""/>
    </Property>
    <Property name="Placement" type="App::PropertyPlacement" status="8388608">
      <PropertyPlacement Px="0" Py="0" Pz="0" Q0="0" Q1="0" Q2="0" Q3="1" A="0" Ox="0" Oy="0" Oz="1"/>
    </Property>
    <Property name="Shape" type="Part::PropertyPartShape">
      <Part ElementMap="0.15.70200.4" brep="1">
<![CDATA[

CASCADE Topology V1, (c) Matra-Datavision
Locations 0
Curve2ds 0
Curves 104
1 -6.3700398676210002 -4.8067890493009999 5.7638289332920003 1 8.2000000000000001e-16 4.0000000000000003e-17 
1 -6.3700398676210002 -4.8067890493009999 -7.8361710667080002 -1.2999999999999999e-16 -1.4000000000000001e-16 1 
1 6.3699601323790001 -4.8067890493009999 -7.8361710667080002 -1 -8.2000000000000001e-16 4.9999999999999999e-17 
1 6.3699601323790001 -4.8067890493009999 5.7638289332920003 1.2999999999999999e-16 1.4000000000000001e-16 -1 
1 0.90996013237899998 0.74321095069900001 7.1288289332919996 8.2000000000000001e-16 -1 -1.4000000000000001e-16 
1 0.90996013237899998 0.74321095069900001 7.1288289332919996 1.2999999999999999e-16 7.0000000000000003e-17 -1 
1 0.90996013237899998 0.74321095069900001 5.9538289332919998 8.2000000000000001e-16 -1 -1.4000000000000001e-16 
1 0.90996013237899998 -0.076789049301369997 7.1288289332919996 1.2999999999999999e-16 2.0000000000000001e-17 -1 
1 -0.91003986762099998 0.74321095069900001 7.1288289332919996 8.2000000000000001e-16 -1 -1.4000000000000001e-16 
1 -0.91003986762099998 0.74321095069900001 7.1288289332919996 1 8.5999999999999997e-16 1.2999999999999999e-16 
1 -0.91003986762099998 -0.076789049301369997 7.1288289332919996 1 8.2000000000000001e-16 1.2999999999999999e-16 
1 -0.91003986762099998 0.74321095069900001 5.9538289332919998 8.2000000000000001e-16 -1 -1.4000000000000001e-16 
1 -0.91003986762099998 0.74321095069900001 5.9538289332919998 -1.2999999999999999e-16 -5.4e-16 1 
1 -0.91003986762099998 -0.076789049301369997 5.9538289332919998 -1.2999999999999999e-16 -4.8999999999999997e-16 1 
1 -0.91003986762099998 -0.076789049301369997 5.9538289332919998 1 5.9000000000000002e-16 1.2999999999999999e-16 
1 -7.8200398676210003 0.74321095069900001 4.7838289332919999 8.2000000000000001e-16 -1 -1.4000000000000001e-16 
1 -7.8200398676210003 0.74321095069900001 4.7838289332919999 -1.2999999999999999e-16 -3.0000000000000001e-17 1 
1 -7.8200398676210003 0.74321095069900001 6.7838289332919999 8.2000000000000001e-16 -1 -1.4000000000000001e-16 
1 -7.8200398676210003 -0.076789049301380002 4.7838289332919999 -1.2999999999999999e-16 0 1 
1 -7.8200398676210003 0.74321095069900001 6.7838289332919999 1 7.0000000000000003e-16 1.2999999999999999e-16 
1 -2.8200398676209999 0.74321095069900001 6.7838289332919999 8.2000000000000001e-16 -1 -1.4000000000000001e-16 
1 -7.8200398676210003 -0.076789049301380002 6.7838289332919999 1 6.8000000000000001e-16 1.2999999999999999e-16 
1 -2.8200398676209999 0.74321095069900001 6.7838289332919999 1.2999999999999999e-16 1.07e-15 -1 
1 -2.8200398676209999 0.74321095069900001 5.9538289332919998 8.2000000000000001e-16 -1 -1.4000000000000001e-16 
1 -2.8200398676209999 -0.076789049301369997 6.7838289332919999 1.2999999999999999e-16 9.6999999999999998e-16 -1 
1 -6.9900398676210003 0.74321095069900001 4.7838289332919999 8.2000000000000001e-16 -1 -1.4000000000000001e-16 
1 -6.9900398676210003 0.74321095069900001 4.7838289332919999 -1 -8.2000000000000001e-16 -1.2999999999999999e-16 
1 -6.9900398676210003 -0.076789049301380002 4.7838289332919999 -1 -8.2000000000000001e-16 -1.2999999999999999e-16 
1 -2.8200398676209999 -0.076789049301369997 5.9538289332919998 -1 -9.5000000000000005e-16 -3.9999999999999999e-16 
1 -6.9900398676210003 -0.076789049301380002 5.9538289332919998 1.2999999999999999e-16 2.5999999999999998e-16 -1 
1 -7.8200398676210003 -0.076789049301380002 -6.8561710667079998 1.2999999999999999e-16 2.8000000000000001e-16 -1 
1 -7.8200398676210003 0.74321095069900001 -6.8561710667079998 8.2000000000000001e-16 -1 -1.4000000000000001e-16 
1 -7.8200398676210003 0.74321095069900001 -6.8561710667079998 1.2999999999999999e-16 2.5000000000000002e-16 -1 
1 -7.8200398676210003 0.74321095069900001 -8.8561710667080007 8.2000000000000001e-16 -1 -1.4000000000000001e-16 
1 -7.8200398676210003 -0.076789049301380002 -8.8561710667080007 1 6.8000000000000001e-16 1.2999999999999999e-16 
1 -7.8200398676210003 0.74321095069900001 -8.8561710667080007 1 7.0000000000000003e-16 1.2999999999999999e-16 
1 -2.8200398676209999 0.74321095069900001 -8.8561710667080007 8.2000000000000001e-16 -1 -1.4000000000000001e-16 
1 -2.8200398676209999 -0.076789049301369997 -8.8561710667080007 -1.2999999999999999e-16 7.0000000000000003e-16 1 
1 -2.8200398676209999 0.74321095069900001 -8.8561710667080007 -1.2999999999999999e-16 7.9000000000000002e-16 1 
1 -2.8200398676209999 0.74321095069900001 -8.0261710667080006 8.2000000000000001e-16 -1 -1.4000000000000001e-16 
1 -6.9900398676210003 -0.076789049301369997 -6.8561710667079998 -1 -8.2000000000000001e-16 -1.2999999999999999e-16 
1 -6.9900398676210003 0.74321095069900001 -6.8561710667079998 8.2000000000000001e-16 -1 -1.4000000000000001e-16 
1 -6.9900398676210003 0.74321095069900001 -6.8561710667079998 -1 -8.2000000000000001e-16 -1.2999999999999999e-16 
1 -6.9900398676210003 -0.076789049301369997 -8.0261710667080006 -1.2999999999999999e-16 -2.0000000000000001e-17 1 
1 -2.8200398676209999 -0.076789049301369997 -8.0261710667080006 -1 -9.5000000000000005e-16 1.4000000000000001e-16 
1 0.90996013237899998 -0.076789049301369997 -9.2011710667079996 -1.2999999999999999e-16 -2.5999999999999998e-16 1 
1 0.90996013237899998 0.74321095069900001 -9.2011710667079996 8.2000000000000001e-16 -1 -1.4000000000000001e-16 
1 0.90996013237899998 0.74321095069900001 -9.2011710667079996 -1.2999999999999999e-16 -2e-16 1 
1 0.90996013237899998 0.74321095069900001 -8.0261710667080006 8.2000000000000001e-16 -1 -1.4000000000000001e-16 
1 -0.91003986762099998 -0.076789049301369997 -9.2011710667079996 1 8.2000000000000001e-16 1.2999999999999999e-16 
1 -0.91003986762099998 0.74321095069900001 -9.2011710667079996 8.2000000000000001e-16 -1 -1.4000000000000001e-16 
1 -0.91003986762099998 0.74321095069900001 -9.2011710667079996 1 8.5999999999999997e-16 1.2999999999999999e-16 
1 -0.91003986762099998 -0.076789049301369997 -8.0261710667080006 1.2999999999999999e-16 -2.2e-16 -1 
1 -0.91003986762099998 0.74321095069900001 -8.0261710667080006 8.2000000000000001e-16 -1 -1.4000000000000001e-16 
1 -0.91003986762099998 0.74321095069900001 -8.0261710667080006 1.2999999999999999e-16 -2.7e-16 -1 
1 -0.91003986762099998 -0.076789049301369997 -8.0261710667080006 1 5.9000000000000002e-16 1.2999999999999999e-16 
1 7.8199601323790002 0.74321095069900001 -6.8561710667079998 8.2000000000000001e-16 -1 -1.4000000000000001e-16 
1 7.8199601323790002 0.74321095069900001 -6.8561710667079998 1.2999999999999999e-16 2.5000000000000002e-16 -1 
1 7.8199601323790002 0.74321095069900001 -8.8561710667080007 8.2000000000000001e-16 -1 -1.4000000000000001e-16 
1 7.8199601323790002 -0.076789049301360005 -6.8561710667079998 1.2999999999999999e-16 2.8000000000000001e-16 -1 
1 7.8199601323790002 0.74321095069900001 -8.8561710667080007 -1 -9.4000000000000009e-16 -1.2999999999999999e-16 
1 2.8199601323789998 0.74321095069900001 -8.8561710667080007 8.2000000000000001e-16 -1 -1.4000000000000001e-16 
1 7.8199601323790002 -0.076789049301360005 -8.8561710667080007 -1 -9.6000000000000002e-16 -1.2999999999999999e-16 
1 2.8199601323789998 0.74321095069900001 -8.8561710667080007 -1.2999999999999999e-16 7.9000000000000002e-16 1 
1 2.8199601323789998 0.74321095069900001 -8.0261710667080006 8.2000000000000001e-16 -1 -1.4000000000000001e-16 
1 2.8199601323789998 -0.076789049301369997 -8.8561710667080007 -1.2999999999999999e-16 7.0000000000000003e-16 1 
1 6.9899601323790002 0.74321095069900001 -6.8561710667079998 8.2000000000000001e-16 -1 -1.4000000000000001e-16 
1 6.9899601323790002 0.74321095069900001 -6.8561710667079998 1 8.2000000000000001e-16 1.2999999999999999e-16 
1 6.9899601323790002 -0.076789049301360005 -6.8561710667079998 1 8.2000000000000001e-16 1.2999999999999999e-16 
1 2.8199601323789998 -0.076789049301369997 -8.0261710667080006 1 6.8999999999999997e-16 3.9999999999999999e-16 
1 6.9899601323790002 -0.076789049301360005 -8.0261710667080006 -1.2999999999999999e-16 -2.0000000000000001e-17 1 
1 7.8199601323790002 -0.076789049301360005 4.7838289332919999 -1.2999999999999999e-16 0 1 
1 7.8199601323790002 0.74321095069900001 4.7838289332919999 8.2000000000000001e-16 -1 -1.4000000000000001e-16 
1 7.8199601323790002 0.74321095069900001 4.7838289332919999 -1.2999999999999999e-16 -3.0000000000000001e-17 1 
1 7.8199601323790002 0.74321095069900001 6.7838289332919999 8.2000000000000001e-16 -1 -1.4000000000000001e-16 
1 7.8199601323790002 -0.076789049301360005 6.7838289332919999 -1 -9.6000000000000002e-16 -1.2999999999999999e-16 
1 7.8199601323790002 0.74321095069900001 6.7838289332919999 -1 -9.4000000000000009e-16 -1.2999999999999999e-16 
1 2.8199601323789998 0.74321095069900001 6.7838289332919999 8.2000000000000001e-16 -1 -1.4000000000000001e-16 
1 2.8199601323789998 -0.076789049301369997 6.7838289332919999 1.2999999999999999e-16 9.6999999999999998e-16 -1 
1 2.8199601323789998 0.74321095069900001 6.7838289332919999 1.2999999999999999e-16 1.07e-15 -1 
1 2.8199601323789998 0.74321095069900001 5.9538289332919998 8.2000000000000001e-16 -1 -1.4000000000000001e-16 
1 6.9899601323790002 -0.076789049301360005 4.7838289332919999 1 8.2000000000000001e-16 1.2999999999999999e-16 
1 6.9899601323790002 0.74321095069900001 4.7838289332919999 8.2000000000000001e-16 -1 -1.4000000000000001e-16 
1 6.9899601323790002 0.74321095069900001 4.7838289332919999 1 8.2000000000000001e-16 1.2999999999999999e-16 
1 6.9899601323790002 0.74321095069900001 -4.5311710667079996 -6.0000000000000001e-17 1.4000000000000001e-16 -1 
1 3.4949601323790001 0.74321095069900001 -8.0261710667080006 -1 -8.2000000000000001e-16 6.0000000000000001e-17 
1 3.4949601323790001 0.74321095069900001 -8.0261710667080006 -1 -8.2000000000000001e-16 6.0000000000000001e-17 
1 -6.9900398676210003 0.74321095069900001 -4.5311710667079996 -0 -1.4000000000000001e-16 1 
1 3.4949601323790001 0.74321095069900001 5.9538289332919998 1 8.2000000000000001e-16 0 
1 3.4949601323790001 0.74321095069900001 5.9538289332919998 1 8.2000000000000001e-16 0 
1 6.9899601323790002 -0.076789049301369997 5.9538289332919998 1.2999999999999999e-16 2.5999999999999998e-16 -1 
1 2.8199601323789998 -0.076789049301369997 5.9538289332919998 1 6.8999999999999997e-16 -1.4000000000000001e-16 
1 -6.9900398676210003 -1.5067890493010001 -8.0261710667080006 0.18435324540905793 -0.98123501588730833 0.056495349399587752 
1 -6.9900398676210003 -1.5067890493010001 5.9538289332919998 0.18435324540905793 -0.98123501588730833 -0.056495349399587752 
1 -6.9900398676210003 -1.5067890493010001 -8.0261710667080006 -4.9999999999999999e-17 -2e-16 1 
1 6.9899601323790002 -1.5067890493010001 5.9538289332919998 -0.18435324540905793 -0.98123501588730833 -0.056495349399587752 
1 -6.9900398676210003 -1.5067890493010001 5.9538289332919998 1 7.6000000000000002e-16 6.0999999999999995e-16 
1 6.9899601323790002 -1.5067890493010001 -8.0261710667080006 -0.18435324540905793 -0.98123501588730833 0.056495349399587752 
1 6.9899601323790002 -1.5067890493010001 -8.0261710667080006 -1 -7.6000000000000002e-16 -5.3000000000000003e-16 
1 6.9899601323790002 -1.5067890493010001 5.9538289332919998 -3.0000000000000001e-17 2e-16 -1 
1 6.9899601323790002 -0.076789049301369997 5.9538289332919998 8.2000000000000001e-16 -1 -1.4000000000000001e-16 
1 6.9899601323790002 -0.076789049301360005 -8.0261710667080006 8.2000000000000001e-16 -1 -1.4000000000000001e-16 
1 -6.9900398676210003 -0.076789049301380002 5.9538289332919998 8.2000000000000001e-16 -1 -1.4000000000000001e-16 
1 -6.9900398676210003 -0.076789049301369997 -8.0261710667080006 8.2000000000000001e-16 -1 -1.4000000000000001e-16 
Polygon3D 0
PolygonOnTriangulations 0
Surfaces 38
1 -3.9867620670180002e-05 -4.8067890493009999 -1.036171066708 8.2000000000000001e-16 -1 -1.4000000000000001e-16 1.2999999999999999e-16 1.4000000000000011e-16 -1 1 8.2000000000000001e-16 1.3000000000000012e-16 
1 -3.986762067819e-05 0.38448688630200001 6.0627205780700004 -1.0000000000000001e-17 -0.057480563292050632 0.99834662559835841 1 8.2015903352286109e-16 5.7237838813457353e-17 -8.2209306678817634e-16 0.99834662559835841 0.057480563292050632 
1 -7.1691042967699996 -0.55370418447500003 -1.036171066708 -0.98280469028651318 -0.18464815393290851 -1.5e-16 -1.264468157972638e-16 -1.3933243205887879e-16 1 -0.18464815393290851 0.98280469028651318 1.1358839662883369e-16 
1 -3.986762067781e-05 0.38448688630200001 -8.1350627114850003 4.0000000000000003e-17 -0.057480563292050632 -0.99834662559835841 -1 -8.2016378536745911e-16 7.1553067757209255e-18 -8.1921903862357499e-16 0.99834662559835841 -0.057480563292050632 
1 7.1690245615289996 -0.55370418447500003 -1.036171066708 0.98280469028651318 -0.18464815393290851 9.9999999999999998e-17 1.2811904136958054e-16 1.4035339222753394e-16 -1 0.18464815393290851 0.98280469028651318 1.6159691665138997e-16 
1 0.90996013237899998 0.74321095069900001 7.1288289332919996 -1 -8.2000000000000001e-16 -1.2999999999999999e-16 -1.2999999999999987e-16 -1.4000000000000001e-16 1 -8.2000000000000001e-16 1 1.3999999999999991e-16 
1 -0.91003986762099998 0.74321095069900001 7.1288289332919996 1.2999999999999999e-16 1.4000000000000001e-16 -1 -1 -8.2000000000000001e-16 -1.3000000000000012e-16 -8.2000000000000001e-16 1 1.3999999999999991e-16 
1 -3.9867620678050002e-05 0.74321095069900001 -1.036171066708 -8.2000000000000001e-16 1 1.4000000000000001e-16 -1.2999999999999999e-16 -1.4000000000000011e-16 1 1 8.2000000000000001e-16 1.3000000000000012e-16 
1 6.9899601323790002 0.79321095069900005 5.9538289332919998 0 1.4000000000000001e-16 -1 -1 -8.2000000000000001e-16 -1.1480000000000002e-31 -8.2000000000000001e-16 1 1.4000000000000001e-16 
1 -3.9867620677379999e-05 -0.076789049301369997 -1.036171066708 8.2000000000000001e-16 -1 -1.4000000000000001e-16 1.2999999999999999e-16 1.4000000000000011e-16 -1 1 8.2000000000000001e-16 1.3000000000000012e-16 
1 -0.91003986762099998 0.74321095069900001 5.9538289332919998 1 8.2000000000000001e-16 1.2999999999999999e-16 1.2999999999999987e-16 1.4000000000000001e-16 -1 -8.2000000000000001e-16 1 1.3999999999999991e-16 
1 -7.8200398676210003 0.74321095069900001 4.7838289332919999 1 8.2000000000000001e-16 1.2999999999999999e-16 1.2999999999999987e-16 1.4000000000000001e-16 -1 -8.2000000000000001e-16 1 1.3999999999999991e-16 
1 -6.9900398676210003 0.74321095069900001 4.7838289332919999 -1.2999999999999999e-16 -1.4000000000000001e-16 1 1 8.2000000000000001e-16 1.3000000000000012e-16 -8.2000000000000001e-16 1 1.3999999999999991e-16 
1 -7.8200398676210003 0.74321095069900001 6.7838289332919999 1.2999999999999999e-16 1.4000000000000001e-16 -1 -1 -8.2000000000000001e-16 -1.3000000000000012e-16 -8.2000000000000001e-16 1 1.3999999999999991e-16 
1 -3.9867620677379999e-05 -0.076789049301369997 -1.036171066708 -8.2000000000000001e-16 1 1.4000000000000001e-16 -1.2999999999999999e-16 -1.4000000000000011e-16 1 1 8.2000000000000001e-16 1.3000000000000012e-16 
1 -2.8200398676209999 0.74321095069900001 6.7838289332919999 -1 -8.2000000000000001e-16 -1.2999999999999999e-16 -1.2999999999999987e-16 -1.4000000000000001e-16 1 -8.2000000000000001e-16 1 1.3999999999999991e-16 
1 -6.9900398676210003 0.79321095069900005 -8.0261710667080006 1 8.2000000000000001e-16 0 -1.1480000000000002e-31 1.4000000000000001e-16 -1 -8.2000000000000001e-16 1 1.4000000000000001e-16 
1 -7.8200398676210003 0.74321095069900001 -6.8561710667079998 -1 -8.2000000000000001e-16 -1.2999999999999999e-16 -1.2999999999999987e-16 -1.4000000000000001e-16 1 -8.2000000000000001e-16 1 1.3999999999999991e-16 
1 -3.9867620677379999e-05 -0.076789049301369997 -1.036171066708 -8.2000000000000001e-16 1 1.4000000000000001e-16 -1.2999999999999999e-16 -1.4000000000000011e-16 1 1 8.2000000000000001e-16 1.3000000000000012e-16 
1 -6.9900398676210003 0.74321095069900001 -6.8561710667079998 -1.2999999999999999e-16 -1.4000000000000001e-16 1 1 8.2000000000000001e-16 1.3000000000000012e-16 -8.2000000000000001e-16 1 1.3999999999999991e-16 
1 -7.8200398676210003 0.74321095069900001 -8.8561710667080007 1.2999999999999999e-16 1.4000000000000001e-16 -1 -1 -8.2000000000000001e-16 -1.3000000000000012e-16 -8.2000000000000001e-16 1 1.3999999999999991e-16 
1 -2.8200398676209999 0.74321095069900001 -8.8561710667080007 1 8.2000000000000001e-16 1.2999999999999999e-16 1.2999999999999987e-16 1.4000000000000001e-16 -1 -8.2000000000000001e-16 1 1.3999999999999991e-16 
1 6.9899601323790002 0.79321095069900005 -8.0261710667080006 6.0000000000000001e-17 -1.4000000000000001e-16 1 1 8.2000000000000001e-16 -5.999999999999989e-17 -8.2000000000000001e-16 1 1.4000000000000006e-16 
1 0.90996013237899998 0.74321095069900001 -9.2011710667079996 1 8.2000000000000001e-16 1.2999999999999999e-16 1.2999999999999987e-16 1.4000000000000001e-16 -1 -8.2000000000000001e-16 1 1.3999999999999991e-16 
1 -3.9867620677379999e-05 -0.076789049301369997 -1.036171066708 8.2000000000000001e-16 -1 -1.4000000000000001e-16 1.2999999999999999e-16 1.4000000000000011e-16 -1 1 8.2000000000000001e-16 1.3000000000000012e-16 
1 -0.91003986762099998 0.74321095069900001 -9.2011710667079996 1.2999999999999999e-16 1.4000000000000001e-16 -1 -1 -8.2000000000000001e-16 -1.3000000000000012e-16 -8.2000000000000001e-16 1 1.3999999999999991e-16 
1 -0.91003986762099998 0.74321095069900001 -8.0261710667080006 -1 -8.2000000000000001e-16 -1.2999999999999999e-16 -1.2999999999999987e-16 -1.4000000000000001e-16 1 -8.2000000000000001e-16 1 1.3999999999999991e-16 
1 7.8199601323790002 0.74321095069900001 -6.8561710667079998 -1 -8.2000000000000001e-16 -1.2999999999999999e-16 -1.2999999999999987e-16 -1.4000000000000001e-16 1 -8.2000000000000001e-16 1 1.3999999999999991e-16 
1 6.9899601323790002 0.74321095069900001 -6.8561710667079998 1.2999999999999999e-16 1.4000000000000001e-16 -1 -1 -8.2000000000000001e-16 -1.3000000000000012e-16 -8.2000000000000001e-16 1 1.3999999999999991e-16 
1 7.8199601323790002 0.74321095069900001 -8.8561710667080007 -1.2999999999999999e-16 -1.4000000000000001e-16 1 1 8.2000000000000001e-16 1.3000000000000012e-16 -8.2000000000000001e-16 1 1.3999999999999991e-16 
1 -3.9867620677379999e-05 -0.076789049301369997 -1.036171066708 -8.2000000000000001e-16 1 1.4000000000000001e-16 -1.2999999999999999e-16 -1.4000000000000011e-16 1 1 8.2000000000000001e-16 1.3000000000000012e-16 
1 2.8199601323789998 0.74321095069900001 -8.8561710667080007 1 8.2000000000000001e-16 1.2999999999999999e-16 1.2999999999999987e-16 1.4000000000000001e-16 -1 -8.2000000000000001e-16 1 1.3999999999999991e-16 
1 6.9899601323790002 0.79321095069900005 -8.0261710667080006 -1 -8.2000000000000001e-16 6.0000000000000001e-17 6.0000000000000112e-17 -1.4000000000000001e-16 1 -8.2000000000000001e-16 1 1.4000000000000006e-16 
1 7.8199601323790002 0.74321095069900001 4.7838289332919999 1 8.2000000000000001e-16 1.2999999999999999e-16 1.2999999999999987e-16 1.4000000000000001e-16 -1 -8.2000000000000001e-16 1 1.3999999999999991e-16 
1 -3.9867620677379999e-05 -0.076789049301369997 -1.036171066708 -8.2000000000000001e-16 1 1.4000000000000001e-16 -1.2999999999999999e-16 -1.4000000000000011e-16 1 1 8.2000000000000001e-16 1.3000000000000012e-16 
1 6.9899601323790002 0.74321095069900001 4.7838289332919999 1.2999999999999999e-16 1.4000000000000001e-16 -1 -1 -8.2000000000000001e-16 -1.3000000000000012e-16 -8.2000000000000001e-16 1 1.3999999999999991e-16 
1 7.8199601323790002 0.74321095069900001 6.7838289332919999 -1.2999999999999999e-16 -1.4000000000000001e-16 1 1 8.2000000000000001e-16 1.3000000000000012e-16 -8.2000000000000001e-16 1 1.3999999999999991e-16 
1 2.8199601323789998 0.74321095069900001 6.7838289332919999 -1 -8.2000000000000001e-16 -1.2999999999999999e-16 -1.2999999999999987e-16 -1.4000000000000001e-16 1 -8.2000000000000001e-16 1 1.3999999999999991e-16 
Triangulations 0

TShapes 250
Ve
1e-07
-6.370039867621 -4.806789049301 5.763828933292
0 0

0101101
*
Ve
1e-07
6.369960132379 -4.806789049301 5.763828933292
0 0

0101101
*
Ed
 1e-07 1 1 0
1  1 0 0 12.74
4 C0 1 0 2 0
0

0101000
+250 0 -249 0 *
Ve
1e-07
-6.370039867621 -4.806789049301 -7.836171066708
0 0

0101101
*
Ed
 1e-07 1 1 0
1  2 0 0 13.6
4 C0 1 0 3 0
0

0101000
+247 0 -250 0 *
Ve
1e-07
6.369960132379 -4.806789049301 -7.836171066708
0 0

0101101
*
Ed
 1e-07 1 1 0
1  3 0 0 12.74
4 C0 1 0 4 0
0

0101000
+245 0 -247 0 *
Ed
 1e-07 1 1 0
1  4 0 0 13.6
4 C0 1 0 5 0
0

0101000
+249 0 -245 0 *
Wi

0101100
-248 0 -246 0 -244 0 -243 0 *
Fa
0  1e-07 1 0

0111000
+242 0 *
Ve
1e-07
0.909960132379 0.743210950699 7.128828933292
0 0

0101101
*
Ve
1e-07
0.909960132379 -0.07678904930137 7.128828933292
0 0

0101101
*
Ed
 1e-07 1 1 0
1  5 0 0 0.82000000000037
4 C0 6 0 7 0
0

0101000
+240 0 -239 0 *
Ve
1e-07
0.909960132379 0.743210950699 5.953828933292
0 0

0101101
*
Ed
 1e-07 1 1 0
1  6 0 0 1.175
4 C0 6 0 8 0
0

0101000
+240 0 -237 0 *
Ve
1e-07
0.909960132379 -0.07678904930137 5.953828933292
0 0

0101101
*
Ed
 1e-07 1 1 0
1  7 0 0 0.82000000000037
4 C0 6 0 9 0
0

0101000
+237 0 -235 0 *
Ed
 1e-07 1 1 0
1  8 0 0 1.175
4 C0 6 0 10 0
0

0101000
+239 0 -235 0 *
Wi

0101100
-238 0 +236 0 +234 0 -233 0 *
Fa
0  1e-07 6 0

0111000
+232 0 *
Ve
1e-07
-0.910039867621 0.743210950699 7.128828933292
0 0

0101101
*
Ve
1e-07
-0.910039867621 -0.07678904930137 7.128828933292
0 0

0101101
*
Ed
 1e-07 1 1 0
1  9 0 0 0.82000000000037
4 C0 7 0 11 0
0

0101000
+230 0 -229 0 *
Ed
 1e-07 1 1 0
1  10 0 0 1.82
4 C0 7 0 8 0
0

0101000
+230 0 -240 0 *
Ed
 1e-07 1 1 0
1  11 0 0 1.82
4 C0 7 0 10 0
0

0101000
+229 0 -239 0 *
Wi

0101100
-228 0 +227 0 +238 0 -226 0 *
Fa
0  1e-07 7 0

0111000
+225 0 *
Ve
1e-07
-0.910039867621 0.743210950699 5.953828933292
0 0

0101101
*
Ve
1e-07
-0.910039867621 -0.07678904930137 5.953828933292
0 0

0101101
*
Ed
 1e-07 1 1 0
1  12 0 0 0.82000000000037
4 C0 11 0 9 0
0

0101000
+223 0 -222 0 *
Ed
 1e-07 1 1 0
1  13 0 0 1.175
4 C0 11 0 8 0
0

0101000
+223 0 -230 0 *
Ed
 1e-07 1 1 0
1  14 0 0 1.175
4 C0 11 0 10 0
0

0101000
+222 0 -229 0 *
Wi

0101100
-221 0 +220 0 +228 0 -219 0 *
Fa
0  1e-07 11 0

0111000
+218 0 *
Ed
 1e-07 1 1 0
1  15 0 0 1.82
4 C0 10 0 9 0
0

0101000
+222 0 -235 0 *
Wi

0101100
-219 0 +216 0 -233 0 -226 0 *
Fa
0  1e-07 10 0

0111000
+215 0 *
Ve
1e-07
-7.820039867621 0.743210950699 4.783828933292
0 0

0101101
*
Ve
1e-07
-7.820039867621 -0.07678904930138 4.783828933292
0 0

0101101
*
Ed
 1e-07 1 1 0
1  16 0 0 0.82000000000038
4 C0 12 0 13 0
0

0101000
+213 0 -212 0 *
Ve
1e-07
-7.820039867621 0.743210950699 6.783828933292
0 0

0101101
*
Ed
 1e-07 1 1 0
1  17 0 0 2
4 C0 12 0 8 0
0

0101000
+213 0 -210 0 *
Ve
1e-07
-7.820039867621 -0.07678904930138 6.783828933292
0 0

0101101
*
Ed
 1e-07 1 1 0
1  18 0 0 0.82000000000038
4 C0 12 0 14 0
0

0101000
+210 0 -208 0 *
Ed
 1e-07 1 1 0
1  19 0 0 2
4 C0 12 0 15 0
0

0101000
+212 0 -208 0 *
Wi

0101100
-211 0 +209 0 +207 0 -206 0 *
Fa
0  1e-07 12 0

0111000
+205 0 *
Ve
1e-07
-2.820039867621 0.743210950699 6.783828933292
0 0

0101101
*
Ed
 1e-07 1 1 0
1  20 0 0 5
4 C0 14 0 8 0
0

0101000
+210 0 -203 0 *
Ve
1e-07
-2.820039867621 -0.07678904930137 6.783828933292
0 0

0101101
*
Ed
 1e-07 1 1 0
1  21 0 0 0.82000000000037
4 C0 14 0 16 0
0

0101000
+203 0 -201 0 *
Ed
 1e-07 1 1 0
1  22 0 0 5
4 C0 14 0 15 0
0

0101000
+208 0 -201 0 *
Wi

0101100
-207 0 +202 0 +200 0 -199 0 *
Fa
0  1e-07 14 0

0111000
+198 0 *
Ve
1e-07
-2.820039867621 0.743210950699 5.953828933292
0 0

0101101
*
Ed
 1e-07 1 1 0
1  23 0 0 0.83
4 C0 16 0 8 0
0

0101000
+203 0 -196 0 *
Ve
1e-07
-2.820039867621 -0.07678904930137 5.953828933292
0 0

0101101
*
Ed
 1e-07 1 1 0
1  24 0 0 0.82000000000037
4 C0 16 0 9 0
0

0101000
+196 0 -194 0 *
Ed
 1e-07 1 1 0
1  25 0 0 0.83
4 C0 16 0 15 0
0

0101000
+201 0 -194 0 *
Wi

0101100
-200 0 +195 0 +193 0 -192 0 *
Fa
0  1e-07 16 0

0111000
+191 0 *
Ve
1e-07
-6.990039867621 0.743210950699 4.783828933292
0 0

0101101
*
Ve
1e-07
-6.990039867621 -0.07678904930138 4.783828933292
0 0

0101101
*
Ed
 1e-07 1 1 0
1  26 0 0 0.82000000000038
4 C0 13 0 17 0
0

0101000
+189 0 -188 0 *
Ed
 1e-07 1 1 0
1  27 0 -0 0.83
4 C0 13 0 8 0
0

0101000
+189 0 -213 0 *
Ed
 1e-07 1 1 0
1  28 0 -0 0.83
4 C0 13 0 15 0
0

0101000
+188 0 -212 0 *
Wi

0101100
-187 0 +186 0 +211 0 -185 0 *
Fa
0  1e-07 13 0

0111000
+184 0 *
Ve
1e-07
-6.990039867621 -0.07678904930138 5.953828933292
0 0

0101101
*
Ed
 1e-07 1 1 0
1  29 0 -0 4.17
4 C0 15 0 9 0
0

0101000
+194 0 -182 0 *
Ed
 1e-07 1 1 0
1  30 0 0 1.17
4 C0 15 0 17 0
0

0101000
+182 0 -188 0 *
Wi

0101100
+206 0 +199 0 +192 0 +181 0 +180 0 +185 0 *
Fa
0  1e-07 15 0

0111000
+179 0 *
Ve
1e-07
-7.820039867621 -0.07678904930138 -6.856171066708
0 0

0101101
*
Ve
1e-07
-7.820039867621 -0.07678904930138 -8.856171066708
0 0

0101101
*
Ed
 1e-07 1 1 0
1  31 0 0 2
4 C0 18 0 19 0
0

0101000
+177 0 -176 0 *
Ve
1e-07
-7.820039867621 0.743210950699 -6.856171066708
0 0

0101101
*
Ed
 1e-07 1 1 0
1  32 0 0 0.82000000000038
4 C0 18 0 20 0
0

0101000
+174 0 -177 0 *
Ve
1e-07
-7.820039867621 0.743210950699 -8.856171066708
0 0

0101101
*
Ed
 1e-07 1 1 0
1  33 0 0 2
4 C0 18 0 8 0
0

0101000
+174 0 -172 0 *
Ed
 1e-07 1 1 0
1  34 0 0 0.82000000000038
4 C0 18 0 21 0
0

0101000
+172 0 -176 0 *
Wi

0101100
-175 0 -173 0 +171 0 +170 0 *
Fa
0  1e-07 18 0

0111000
+169 0 *
Ve
1e-07
-2.820039867621 -0.07678904930137 -8.856171066708
0 0

0101101
*
Ed
 1e-07 1 1 0
1  35 0 0 5
4 C0 21 0 19 0
0

0101000
+176 0 -167 0 *
Ve
1e-07
-2.820039867621 0.743210950699 -8.856171066708
0 0

0101101
*
Ed
 1e-07 1 1 0
1  36 0 0 5
4 C0 21 0 8 0
0

0101000
+172 0 -165 0 *
Ed
 1e-07 1 1 0
1  37 0 0 0.82000000000037
4 C0 21 0 22 0
0

0101000
+165 0 -167 0 *
Wi

0101100
-166 0 -170 0 +164 0 +163 0 *
Fa
0  1e-07 21 0

0111000
+162 0 *
Ve
1e-07
-2.820039867621 -0.07678904930137 -8.026171066708
0 0

0101101
*
Ed
 1e-07 1 1 0
1  38 0 0 0.83
4 C0 22 0 19 0
0

0101000
+167 0 -160 0 *
Ve
1e-07
-2.820039867621 0.743210950699 -8.026171066708
0 0

0101101
*
Ed
 1e-07 1 1 0
1  39 0 0 0.83
4 C0 22 0 8 0
0

0101000
+165 0 -158 0 *
Ed
 1e-07 1 1 0
1  40 0 0 0.82000000000037
4 C0 22 0 23 0
0

0101000
+158 0 -160 0 *
Wi

0101100
-159 0 -163 0 +157 0 +156 0 *
Fa
0  1e-07 22 0

0111000
+155 0 *
Ve
1e-07
-6.990039867621 -0.07678904930137 -6.856171066708
0 0

0101101
*
Ed
 1e-07 1 1 0
1  41 0 -0 0.83
4 C0 20 0 19 0
0

0101000
+153 0 -177 0 *
Ve
1e-07
-6.990039867621 0.743210950699 -6.856171066708
0 0

0101101
*
Ed
 1e-07 1 1 0
1  42 0 0 0.82000000000037
4 C0 20 0 17 0
0

0101000
+151 0 -153 0 *
Ed
 1e-07 1 1 0
1  43 0 -0 0.83
4 C0 20 0 8 0
0

0101000
+151 0 -174 0 *
Wi

0101100
-152 0 -150 0 +149 0 +173 0 *
Fa
0  1e-07 20 0

0111000
+148 0 *
Ve
1e-07
-6.990039867621 -0.07678904930137 -8.026171066708
0 0

0101101
*
Ed
 1e-07 1 1 0
1  44 0 0 1.17
4 C0 19 0 17 0
0

0101000
+146 0 -153 0 *
Ed
 1e-07 1 1 0
1  45 0 0 4.17
4 C0 19 0 23 0
0

0101000
+160 0 -146 0 *
Wi

0101100
-152 0 -145 0 -144 0 -159 0 -166 0 -175 0 *
Fa
0  1e-07 19 0

0111000
+143 0 *
Ve
1e-07
0.909960132379 -0.07678904930137 -9.201171066708
0 0

0101101
*
Ve
1e-07
0.909960132379 -0.07678904930137 -8.026171066708
0 0

0101101
*
Ed
 1e-07 1 1 0
1  46 0 0 1.175
4 C0 24 0 25 0
0

0101000
+141 0 -140 0 *
Ve
1e-07
0.909960132379 0.743210950699 -9.201171066708
0 0

0101101
*
Ed
 1e-07 1 1 0
1  47 0 0 0.82000000000037
4 C0 24 0 26 0
0

0101000
+138 0 -141 0 *
Ve
1e-07
0.909960132379 0.743210950699 -8.026171066708
0 0

0101101
*
Ed
 1e-07 1 1 0
1  48 0 0 1.175
4 C0 24 0 8 0
0

0101000
+138 0 -136 0 *
Ed
 1e-07 1 1 0
1  49 0 0 0.82000000000037
4 C0 24 0 23 0
0

0101000
+136 0 -140 0 *
Wi

0101100
-139 0 -137 0 +135 0 +134 0 *
Fa
0  1e-07 24 0

0111000
+133 0 *
Ve
1e-07
-0.910039867621 -0.07678904930137 -9.201171066708
0 0

0101101
*
Ed
 1e-07 1 1 0
1  50 0 0 1.82
4 C0 26 0 25 0
0

0101000
+131 0 -141 0 *
Ve
1e-07
-0.910039867621 0.743210950699 -9.201171066708
0 0

0101101
*
Ed
 1e-07 1 1 0
1  51 0 0 0.82000000000037
4 C0 26 0 27 0
0

0101000
+129 0 -131 0 *
Ed
 1e-07 1 1 0
1  52 0 0 1.82
4 C0 26 0 8 0
0

0101000
+129 0 -138 0 *
Wi

0101100
-130 0 -128 0 +127 0 +137 0 *
Fa
0  1e-07 26 0

0111000
+126 0 *
Ve
1e-07
-0.910039867621 -0.07678904930137 -8.026171066708
0 0

0101101
*
Ed
 1e-07 1 1 0
1  53 0 0 1.175
4 C0 27 0 25 0
0

0101000
+124 0 -131 0 *
Ve
1e-07
-0.910039867621 0.743210950699 -8.026171066708
0 0

0101101
*
Ed
 1e-07 1 1 0
1  54 0 0 0.82000000000037
4 C0 27 0 23 0
0

0101000
+122 0 -124 0 *
Ed
 1e-07 1 1 0
1  55 0 0 1.175
4 C0 27 0 8 0
0

0101000
+122 0 -129 0 *
Wi

0101100
-123 0 -121 0 +120 0 +128 0 *
Fa
0  1e-07 27 0

0111000
+119 0 *
Ed
 1e-07 1 1 0
1  56 0 0 1.82
4 C0 25 0 23 0
0

0101000
+124 0 -140 0 *
Wi

0101100
-117 0 +123 0 +130 0 +139 0 *
Fa
0  1e-07 25 0

0111000
+116 0 *
Ve
1e-07
7.819960132379 0.743210950699 -6.856171066708
0 0

0101101
*
Ve
1e-07
7.819960132379 -0.07678904930136 -6.856171066708
0 0

0101101
*
Ed
 1e-07 1 1 0
1  57 0 0 0.82000000000036
4 C0 28 0 29 0
0

0101000
+114 0 -113 0 *
Ve
1e-07
7.819960132379 0.743210950699 -8.856171066708
0 0

0101101
*
Ed
 1e-07 1 1 0
1  58 0 0 2
4 C0 28 0 8 0
0

0101000
+114 0 -111 0 *
Ve
1e-07
7.819960132379 -0.07678904930136 -8.856171066708
0 0

0101101
*
Ed
 1e-07 1 1 0
1  59 0 0 0.82000000000036
4 C0 28 0 30 0
0

0101000
+111 0 -109 0 *
Ed
 1e-07 1 1 0
1  60 0 0 2
4 C0 28 0 31 0
0

0101000
+113 0 -109 0 *
Wi

0101100
-112 0 +110 0 +108 0 -107 0 *
Fa
0  1e-07 28 0

0111000
+106 0 *
Ve
1e-07
2.819960132379 0.743210950699 -8.856171066708
0 0

0101101
*
Ed
 1e-07 1 1 0
1  61 0 -0 5
4 C0 30 0 8 0
0

0101000
+111 0 -104 0 *
Ve
1e-07
2.819960132379 -0.07678904930137 -8.856171066708
0 0

0101101
*
Ed
 1e-07 1 1 0
1  62 0 0 0.82000000000037
4 C0 30 0 32 0
0

0101000
+104 0 -102 0 *
Ed
 1e-07 1 1 0
1  63 0 -0 5
4 C0 30 0 31 0
0

0101000
+109 0 -102 0 *
Wi

0101100
-108 0 +103 0 +101 0 -100 0 *
Fa
0  1e-07 30 0

0111000
+99 0 *
Ve
1e-07
2.819960132379 0.743210950699 -8.026171066708
0 0

0101101
*
Ed
 1e-07 1 1 0
1  64 0 0 0.83
4 C0 32 0 8 0
0

0101000
+104 0 -97 0 *
Ve
1e-07
2.819960132379 -0.07678904930137 -8.026171066708
0 0

0101101
*
Ed
 1e-07 1 1 0
1  65 0 0 0.82000000000037
4 C0 32 0 23 0
0

0101000
+97 0 -95 0 *
Ed
 1e-07 1 1 0
1  66 0 0 0.83
4 C0 32 0 31 0
0

0101000
+102 0 -95 0 *
Wi

0101100
-101 0 +96 0 +94 0 -93 0 *
Fa
0  1e-07 32 0

0111000
+92 0 *
Ve
1e-07
6.989960132379 0.743210950699 -6.856171066708
0 0

0101101
*
Ve
1e-07
6.989960132379 -0.07678904930136 -6.856171066708
0 0

0101101
*
Ed
 1e-07 1 1 0
1  67 0 0 0.82000000000036
4 C0 29 0 33 0
0

0101000
+90 0 -89 0 *
Ed
 1e-07 1 1 0
1  68 0 0 0.83
4 C0 29 0 8 0
0

0101000
+90 0 -114 0 *
Ed
 1e-07 1 1 0
1  69 0 0 0.83
4 C0 29 0 31 0
0

0101000
+89 0 -113 0 *
Wi

0101100
-88 0 +87 0 +112 0 -86 0 *
Fa
0  1e-07 29 0

0111000
+85 0 *
Ve
1e-07
6.989960132379 -0.07678904930136 -8.026171066708
0 0

0101101
*
Ed
 1e-07 1 1 0
1  70 0 0 4.17
4 C0 31 0 23 0
0

0101000
+95 0 -83 0 *
Ed
 1e-07 1 1 0
1  71 0 0 1.17
4 C0 31 0 33 0
0

0101000
+83 0 -89 0 *
Wi

0101100
+107 0 +100 0 +93 0 +82 0 +81 0 +86 0 *
Fa
0  1e-07 31 0

0111000
+80 0 *
Ve
1e-07
7.819960132379 -0.07678904930136 4.783828933292
0 0

0101101
*
Ve
1e-07
7.819960132379 -0.07678904930136 6.783828933292
0 0

0101101
*
Ed
 1e-07 1 1 0
1  72 0 0 2
4 C0 34 0 35 0
0

0101000
+78 0 -77 0 *
Ve
1e-07
7.819960132379 0.743210950699 4.783828933292
0 0

0101101
*
Ed
 1e-07 1 1 0
1  73 0 0 0.82000000000036
4 C0 34 0 36 0
0

0101000
+75 0 -78 0 *
Ve
1e-07
7.819960132379 0.743210950699 6.783828933292
0 0

0101101
*
Ed
 1e-07 1 1 0
1  74 0 0 2
4 C0 34 0 8 0
0

0101000
+75 0 -73 0 *
Ed
 1e-07 1 1 0
1  75 0 0 0.82000000000036
4 C0 34 0 37 0
0

0101000
+73 0 -77 0 *
Wi

0101100
-76 0 -74 0 +72 0 +71 0 *
Fa
0  1e-07 34 0

0111000
+70 0 *
Ve
1e-07
2.819960132379 -0.07678904930137 6.783828933292
0 0

0101101
*
Ed
 1e-07 1 1 0
1  76 0 -0 5
4 C0 37 0 35 0
0

0101000
+77 0 -68 0 *
Ve
1e-07
2.819960132379 0.743210950699 6.783828933292
0 0

0101101
*
Ed
 1e-07 1 1 0
1  77 0 -0 5
4 C0 37 0 8 0
0

0101000
+73 0 -66 0 *
Ed
 1e-07 1 1 0
1  78 0 0 0.82000000000037
4 C0 37 0 38 0
0

0101000
+66 0 -68 0 *
Wi

0101100
-67 0 -71 0 +65 0 +64 0 *
Fa
0  1e-07 37 0

0111000
+63 0 *
Ve
1e-07
2.819960132379 -0.07678904930137 5.953828933292
0 0

0101101
*
Ed
 1e-07 1 1 0
1  79 0 0 0.83
4 C0 38 0 35 0
0

0101000
+68 0 -61 0 *
Ve
1e-07
2.819960132379 0.743210950699 5.953828933292
0 0

0101101
*
Ed
 1e-07 1 1 0
1  80 0 0 0.83
4 C0 38 0 8 0
0

0101000
+66 0 -59 0 *
Ed
 1e-07 1 1 0
1  81 0 0 0.82000000000037
4 C0 38 0 9 0
0

0101000
+59 0 -61 0 *
Wi

0101100
-60 0 -64 0 +58 0 +57 0 *
Fa
0  1e-07 38 0

0111000
+56 0 *
Ve
1e-07
6.989960132379 -0.07678904930136 4.783828933292
0 0

0101101
*
Ed
 1e-07 1 1 0
1  82 0 0 0.83
4 C0 36 0 35 0
0

0101000
+54 0 -78 0 *
Ve
1e-07
6.989960132379 0.743210950699 4.783828933292
0 0

0101101
*
Ed
 1e-07 1 1 0
1  83 0 0 0.82000000000036
4 C0 36 0 33 0
0

0101000
+52 0 -54 0 *
Ed
 1e-07 1 1 0
1  84 0 0 0.83
4 C0 36 0 8 0
0

0101000
+52 0 -75 0 *
Wi

0101100
-53 0 -51 0 +50 0 +74 0 *
Fa
0  1e-07 36 0

0111000
+49 0 *
Ed
 1e-07 1 1 0
1  85 0 -9.315 2.325
4 C0 8 0 33 0
0

0101000
+52 0 -90 0 *
Ed
 1e-07 1 1 0
1  86 0 0.675 2.585
4 C0 8 0 23 0
0

0101000
+97 0 -136 0 *
Ed
 1e-07 1 1 0
1  87 0 4.405 6.315
4 C0 8 0 23 0
0

0101000
+122 0 -158 0 *
Ed
 1e-07 1 1 0
1  88 0 -2.325 9.315
4 C0 8 0 17 0
0

0101000
+151 0 -189 0 *
Ed
 1e-07 1 1 0
1  89 0 -6.315 -4.405
4 C0 8 0 9 0
0

0101000
+196 0 -223 0 *
Ed
 1e-07 1 1 0
1  90 0 -2.585 -0.675
4 C0 8 0 9 0
0

0101000
+237 0 -59 0 *
Wi

0101100
-72 0 -50 0 +47 0 +87 0 +110 0 +103 0 +96 0 +46 0 -135 0 -127 0 
-120 0 +45 0 -157 0 -164 0 -171 0 -149 0 +44 0 +186 0 +209 0 +202 0 
+195 0 +43 0 +220 0 +227 0 +236 0 +42 0 -58 0 -65 0 *
Fa
0  1e-07 8 0

0111000
+41 0 *
Ve
1e-07
6.989960132379 -0.07678904930137 5.953828933292
0 0

0101101
*
Ed
 1e-07 1 1 0
1  91 0 0 1.17
4 C0 35 0 33 0
0

0101000
+39 0 -54 0 *
Ed
 1e-07 1 1 0
1  92 0 0 4.17
4 C0 35 0 9 0
0

0101000
+61 0 -39 0 *
Wi

0101100
-53 0 -38 0 -37 0 -60 0 -67 0 -76 0 *
Fa
0  1e-07 35 0

0111000
+36 0 *
Ve
1e-07
-6.990039867621 -1.506789049301 -8.026171066708
0 0

0101101
*
Ed
 1e-07 1 1 0
1  93 0 0 3.36310868096766
4 C0 3 0 4 0
0

0101000
+34 0 -247 0 *
Ve
1e-07
-6.990039867621 -1.506789049301 5.953828933292
0 0

0101101
*
Ed
 1e-07 1 1 0
1  94 0 0 3.36310868096766
4 C0 3 0 2 0
0

0101000
+32 0 -250 0 *
Ed
 1e-07 1 1 0
1  95 0 0 13.98
4 C0 3 0 17 0
0

0101000
+34 0 -32 0 *
Wi

0101100
+33 0 +246 0 -31 0 -30 0 *
Fa
0  1e-07 3 0

0111000
+29 0 *
Ve
1e-07
6.989960132379 -1.506789049301 5.953828933292
0 0

0101101
*
Ed
 1e-07 1 1 0
1  96 0 -0 3.36310868096766
4 C0 2 0 5 0
0

0101000
+27 0 -249 0 *
Ed
 1e-07 1 1 0
1  97 0 0 13.98
4 C0 2 0 9 0
0

0101000
+32 0 -27 0 *
Wi

0101100
+31 0 +248 0 -26 0 -25 0 *
Fa
0  1e-07 2 0

0111000
+24 0 *
Ve
1e-07
6.989960132379 -1.506789049301 -8.026171066708
0 0

0101101
*
Ed
 1e-07 1 1 0
1  98 0 0 3.36310868096766
4 C0 4 0 5 0
0

0101000
+22 0 -245 0 *
Ed
 1e-07 1 1 0
1  99 0 -0 13.98
4 C0 4 0 23 0
0

0101000
+22 0 -34 0 *
Wi

0101100
+21 0 +244 0 -33 0 -20 0 *
Fa
0  1e-07 4 0

0111000
+19 0 *
Ed
 1e-07 1 1 0
1  100 0 0 13.98
4 C0 5 0 33 0
0

0101000
+27 0 -22 0 *
Wi

0101100
+26 0 +243 0 -21 0 -17 0 *
Fa
0  1e-07 5 0

0111000
+16 0 *
Ed
 1e-07 1 1 0
1  101 0 0 1.42999999999963
4 C0 33 0 9 0
0

0101000
+39 0 -27 0 *
Ed
 1e-07 1 1 0
1  102 0 0 1.42999999999964
4 C0 33 0 23 0
0

0101000
+83 0 -22 0 *
Wi

0101100
-47 0 +51 0 -38 0 +14 0 +17 0 -13 0 +81 0 -88 0 *
Fa
0  1e-07 33 0

0111000
-12 0 *
Ed
 1e-07 1 1 0
1  103 0 0 1.42999999999962
4 C0 9 0 17 0
0

0101000
+182 0 -32 0 *
Wi

0101100
-43 0 +193 0 +181 0 +10 0 +25 0 -14 0 -37 0 -57 0 -42 0 +234 0 
-216 0 -221 0 *
Fa
0  1e-07 9 0

0111000
-9 0 *
Ed
 1e-07 1 1 0
1  104 0 0 1.42999999999963
4 C0 23 0 17 0
0

0101000
+146 0 -34 0 *
Wi

0101100
-45 0 +121 0 +117 0 -134 0 -46 0 +94 0 +82 0 +13 0 +20 0 -7 0 
-144 0 -156 0 *
Fa
0  1e-07 23 0

0111000
-6 0 *
Wi

0101100
-44 0 +150 0 -145 0 +7 0 +30 0 -10 0 +180 0 -187 0 *
Fa
0  1e-07 17 0

0111000
-4 0 *
Sh

0101100
+241 0 -231 0 -224 0 -217 0 +214 0 -204 0 -197 0 -190 0 -183 0 -178 0 
+168 0 +161 0 +154 0 +147 0 -142 0 +132 0 +125 0 +118 0 +115 0 -105 0 
-98 0 -91 0 -84 0 -79 0 +69 0 +62 0 +55 0 +48 0 +40 0 -35 0 
+28 0 +23 0 +18 0 +15 0 -11 0 -8 0 -5 0 -3 0 *
So

0100000
+2 0 *

+1 0 ]]>
      </Part>
      <ElementMap/>
    </Property>
    <Property name="TreeRank" type="App::PropertyInteger" status="2184">
      <Integer value="507"/>
    </Property>
    <Property name="Visibility" type="App::PropertyBool" status="648">
      <Bool value="false"/>
    </Property>
  </Properties>
</Object>
</Document>
